{
  "lastUpdate": "2026-02-13",
  "source": "TradingEconomics + COT",
  "methodology": "Web scraping with automatic unit conversion",
  "units": {
    "gdp": "Trillions USD",
    "tradeBalance": "Millions USD (monthly)",
    "retailSales": "% Month-over-Month",
    "wageGrowth": "% Year-over-Year",
    "manufacturingPMI": "Index (>50 = expansion)",
    "cotPositioning": "Net contracts (positive = bullish)",
    "other": "Percentages"
  },
  "data": {
    "gdp": 29185.0,
    "gdpGrowth": 4.4,
    "inflation": 2.4,
    "unemployment": 4.3,
    "debt": 124.0,
    "currentAccount": -3.9,
    "production": 2.0,
    "tradeBalance": -56830.0,
    "retailSales": 0.0,
    "wageGrowth": 3.76,
    "manufacturingPMI": 52.4
  }
}